{"entries":[{"id":"UbiCube","locationType":"Resources","assetName":"UbiCube"},{"id":"UnityCube","locationType":"AssetBundles","abName":"asset_cubes_2","assetName":"UnityCube"},{"id":"unknownMaterial","locationType":"Resources","assetName":"unknownMaterial"},{"id":"HDLogo","locationType":"Resources","assetName":"HDLogo"},{"id":"UbiLogoSprite","locationType":"Resources","assetName":"UbiLogoSprite"},{"id":"OnlyPlatformTexture","locationType":"AssetBundles","abName":"only_platform","assetName":"onlyPlatformTexture"},{"id":"HDCube","variant":"high","locationType":"Resources","assetName":"HDCube"},{"id":"HDCube","variant":"low","locationType":"Resources","assetName":"HDCube"},{"id":"SC_Cubes","variant":"high","locationType":"AssetBundles","abName":"scene_cubes_high","assetName":"SC_Cubes"},{"id":"SC_Cubes","variant":"low","locationType":"AssetBundles","abName":"scene_cubes_low","assetName":"SC_Cubes"}]}
