{"urlBase":"localhost","assets":{"missionOtherModifiersDefinitions.xml":871506559,"petMovementDefinitions.xml":521324111,"freezeConstantDefinitions.xml":2693525322,"seasonsDefinitions.xml":3478296861,"disguiseEquipDefinitions.xml":3049561507,"shopPacksDefinitions.xml":2798103504,"spawnersDragonBurnDefinitions.xml":1117616709,"initialSettings.xml":2809992672,"petDefinitions.xml":2597643266,"goldenEggDefinitions.xml":1913402501,"german.txt":1426025017,"japanese.txt":256541756,"simplified_chinese.txt":232568292,"disguiseRewardDistributionDefinitions.xml":3065636808,"achievementsDefinitions.xml":75384901,"dragonProgressionDefinitions.xml":4114604592,"mapUpgradesDefinitions.xml":3953421948,"dragonSkillProgressionDefinitions.xml":1128958180,"eggRewardDefinitions.xml":4061249441,"dragonTierDefinitions.xml":3183601730,"italian.txt":3303348910,"entityDefinitions.xml":1910191521,"missingRessourcesVariablesDefinitions.xml":3862741544,"missionDragonModifiersDefinitions.xml":2333529185,"korean.txt":1471546906,"featureDeviceSettings.xml":460548965,"featureProfileSettings.xml":2576857965,"PM_level_0_area2.xml":2410840492,"burnRelation.xml":2556450180,"missingRessourcesTiersDefinitions.xml":270196348,"petCategoryDefinitions.xml":742796438,"missionTypeDefinitions.xml":3768127879,"eventCalendarDefinitions.xml":2765427843,"PM_level_0_area3.xml":2373219219,"missionDifficultyDefinitions.xml":1209162235,"disguisesDefinitions.xml":4205112763,"dragonSkillDefinitions.xml":1462201858,"missionDifficultyModifiersDefinitions.xml":3904976128,"english.txt":2225059559,"eggDefinitions.xml":2314166975,"hungryLettersDefinitions.xml":163347573,"dragonSettings.xml":4132083946,"entityDragonBurnDefinitions.xml":3068697516,"scoreMultiplierDefinitions.xml":948443328,"localizationDefinitions.xml":1512379213,"disguisePowerUpsDefinitions.xml":2924863135,"dragonHealthModifiersDefinitions.xml":743677566,"chestRewardDefinitions.xml":772729233,"eventGoalDefinitions.xml":3601648340,"gameSettings.xml":589047207,"missionDefinitions.xml":1929756339,"decorationDefinitions.xml":1366477803,"missionsDefinitions.xml":4237560965,"survivalBonusDefinitions.xml":2668619265,"PM_level_0_area1.xml":2698185828,"deviceRatingSettings.xml":566233176,"french.txt":1782418653,"levelDefinitions.xml":1422773354,"dragonDefinitions.xml":2739035106,"rarityDefinitions.xml":2076149884,"powerUpsDefinitions.xml":1406364319,"entityCategoryDefinitions.xml":4246502157,"holdPreyTierSettingsDefinitions.xml":1534708602,"russian.txt":1412070665,"brazilian.txt":3180799924,"eventStepsDefinitions.xml":3202405322,"trad chinese.txt":3982666522,"spanish.txt":2785259140},"release":"1.2","deltas":0,"revision":5}