{"spawners":[ {"prefab":"Air/PF_BatBig", "logicUnits":"1"}, {"prefab":"Air/PF_BatSmall", "logicUnits":"1"}, {"prefab":"Air/PF_Canary_00", "logicUnits":"1"}, {"prefab":"Air/PF_Canary_01", "logicUnits":"1"}, {"prefab":"Air/PF_Canary_02", "logicUnits":"1"}, {"prefab":"Air/PF_Canary_03", "logicUnits":"1"}, {"prefab":"Air/PF_Canary_Bg", "logicUnits":"1"}, {"prefab":"Air/PF_Crow", "logicUnits":"1"}, {"prefab":"Air/PF_DragonEnemyDevil", "logicUnits":"1"}, {"prefab":"Air/PF_EnemyRhino", "logicUnits":"1"}, {"prefab":"Air/PF_FlyingPig", "logicUnits":"1"}, {"prefab":"Air/PF_Ghost_01", "logicUnits":"1"}, {"prefab":"Air/PF_Hawk", "logicUnits":"1"}, {"prefab":"Air/PF_MineBig", "logicUnits":"1"}, {"prefab":"Air/PF_MineBig_Static", "logicUnits":"1"}, {"prefab":"Air/PF_MineSmall_01", "logicUnits":"1"}, {"prefab":"Air/PF_MineSmall_01_Static", "logicUnits":"1"}, {"prefab":"Air/PF_Owl", "logicUnits":"1"}, {"prefab":"Air/PF_OwlBig", "logicUnits":"1"}, {"prefab":"Air/PF_Starling", "logicUnits":"1"}, {"prefab":"Air/PF_Witch", "logicUnits":"1"}, {"prefab":"Cage/PF_Cage", "logicUnits":"1"}, {"prefab":"Cage/PF_HangingCage", "logicUnits":"1"}, {"prefab":"Junk/PF_GoodJunkBottle", "logicUnits":"1"}, {"prefab":"Surface/PF_Archer_01", "logicUnits":"1"}, {"prefab":"Surface/PF_Archer_02", "logicUnits":"1"}, {"prefab":"Surface/PF_Cow", "logicUnits":"1"}, {"prefab":"Surface/PF_Horse", "logicUnits":"1"}, {"prefab":"Surface/PF_HorseStatic", "logicUnits":"1"}, {"prefab":"Surface/PF_Richman", "logicUnits":"1"}, {"prefab":"Surface/PF_Sheep_01", "logicUnits":"1"}, {"prefab":"Surface/PF_Soldier_01", "logicUnits":"1"}, {"prefab":"Surface/PF_SpiderGreen", "logicUnits":"1"}, {"prefab":"Surface/PF_SpiderGreenTurret", "logicUnits":"1"}, {"prefab":"Surface/PF_SpiderRed", "logicUnits":"1"}, {"prefab":"Surface/PF_SpiderSmall", "logicUnits":"1"}, {"prefab":"Surface/PF_Villager_01", "logicUnits":"1"}, {"prefab":"Surface/PF_Villager_02", "logicUnits":"1"}, {"prefab":"Surface/PF_Villager_Locked", "logicUnits":"1"}, {"prefab":"Water/PF_Fish_Generic_01", "logicUnits":"1"}, {"prefab":"Water/PF_Fish_Generic_02", "logicUnits":"1"}, {"prefab":"Water/PF_Fish_Generic_03", "logicUnits":"1"}, {"prefab":"Water/PF_Piranha", "logicUnits":"1"}, {"prefab":"Water/PF_Tropical_fish", "logicUnits":"1"}, {"prefab":"Air/PF_EnemyBaby", "logicUnits":"1"}, {"prefab":"Surface/PF_Catapulter", "logicUnits":"1"} ]}