{"urlBase":"http://10.44.4.76:7888/Android/","assets":{"dragon_alien":{"crc32":182082981,"size":6181347},"assets_medieval_village_castle":{"crc32":130888728,"size":4311371},"assets_medieval_village_castle_dark":{"crc32":172073285,"size":6219901},"assets_medieval_village_dark":{"crc32":771326895,"size":2131930},"dragon_alien_shared":{"crc32":3666748066,"size":875808},"dragon_shared":{"crc32":3990044385,"size":25721},"dragon_shared_ingame":{"crc32":555051393,"size":506875},"npc_medieval_castle":{"crc32":80422914,"size":2412555},"npc_medieval_village_castle":{"crc32":2373526323,"size":1722476},"npc_medieval_village_castle_dark":{"crc32":1613411753,"size":5378200},"npc_medieval_village_dark":{"crc32":1369802995,"size":1466013},"npc_shared":{"crc32":3925254988,"size":217656},"particles_medieval_village_castle_dark":{"crc32":3796481429,"size":224700},"particles_medieval_village_dark":{"crc32":3320933574,"size":31931},"particles_shared":{"crc32":2298806191,"size":1890988},"pets_07":{"crc32":713232956,"size":2665112},"pets_local":{"crc32":2408439777,"size":7556677},"shared":{"crc32":4019001714,"size":3345163},"dragon_balrog":{"crc32":1047645398,"size":5533758},"dragon_balrog_shared":{"crc32":2262717119,"size":819138},"dragon_bug":{"crc32":4235209201,"size":5220417},"dragon_bug_shared":{"crc32":2615023019,"size":1184992},"dragon_chinese":{"crc32":973074648,"size":3613227},"dragon_chinese_shared":{"crc32":1854612969,"size":780503},"dragon_classic":{"crc32":1670740152,"size":9040682},"dragon_classic_shared":{"crc32":2695868211,"size":1022101},"dragon_dark":{"crc32":1488228814,"size":5996451},"dragon_dark_shared":{"crc32":642490740,"size":126396},"pets_08":{"crc32":4271049294,"size":2051546},"dragon_devil":{"crc32":3064440909,"size":6814185},"dragon_devil_shared":{"crc32":3167055341,"size":365187},"dragon_dino":{"crc32":2608194341,"size":3605025},"dragon_dino_shared":{"crc32":3678872525,"size":91923},"dragon_electric":{"crc32":1613657187,"size":735105},"dragon_electric_shared":{"crc32":2328547950,"size":181470},"dragon_fat":{"crc32":4147567056,"size":5050282},"dragon_fat_shared":{"crc32":2486798881,"size":51407},"dragon_goldheist":{"crc32":1355530434,"size":4703634},"dragon_goldheist_shared":{"crc32":2049525704,"size":1111452},"dragon_hedgehog":{"crc32":2008742403,"size":2058848},"dragon_hedgehog_shared":{"crc32":1151867552,"size":41221},"dragon_helicopter":{"crc32":2109179477,"size":2093904},"dragon_helicopter_shared":{"crc32":1873266335,"size":423508},"dragon_ice":{"crc32":347976365,"size":1499811},"dragon_ice_shared":{"crc32":2982989087,"size":189501},"dragon_jawfrey":{"crc32":3425887806,"size":6182906},"dragon_jawfrey_shared":{"crc32":3801192569,"size":294284},"dragon_titan":{"crc32":2362797456,"size":7777609},"dragon_titan_shared":{"crc32":2836141578,"size":1172335},"pets_04":{"crc32":3626382250,"size":1275907},"npc_medieval_dark":{"crc32":3096584330,"size":3136027},"scene_medieval_castle":{"crc32":881284193,"size":2708340},"assets_medieval_castle":{"crc32":3395213033,"size":9902974},"assets_medieval_castle_dark":{"crc32":2375068101,"size":82255},"particles_medieval_castle":{"crc32":1047107145,"size":49834},"sounds_medieval_castle":{"crc32":2251997782,"size":2295894},"sounds_medieval_village_castle":{"crc32":37538830,"size":1088521},"sounds_medieval_village_castle_dark":{"crc32":3022926663,"size":1893154},"spawners_medieval_castle":{"crc32":1353267824,"size":7389},"spawners_medieval_village_castle":{"crc32":3798089196,"size":10182},"spawners_medieval_village_castle_dark":{"crc32":653609281,"size":13055},"scene_medieval_dark":{"crc32":2636266618,"size":810403},"assets_medieval_dark":{"crc32":2791396871,"size":7040229},"particles_medieval_dark":{"crc32":332755529,"size":205723},"sounds_medieval_dark":{"crc32":1658017585,"size":2568382},"sounds_medieval_village_dark":{"crc32":3230442434,"size":154667},"spawners_medieval_dark":{"crc32":3380993251,"size":11782},"spawners_medieval_village_dark":{"crc32":2284562960,"size":4492},"pets_01":{"crc32":673731008,"size":1259046},"pets_02":{"crc32":1152751800,"size":1318210},"pets_03":{"crc32":165927637,"size":1277490},"pets_05":{"crc32":4243810015,"size":1357109},"pets_06":{"crc32":401035810,"size":2599677},"pets_09":{"crc32":3553335107,"size":1199252}}}
