<Definitions>
	<Definition sku="leprechaun_hat" category="head" tidName="TID_LEPRECHAUN_HAT" />
	<Definition sku="Foil_Paper_hat" category="head" tidName="TID_FOIL_PAPER_HAT" />
	<Definition sku="alien_mask" category="head" tidName="TID_ALIEN_MASK" />
	<Definition sku="anniversary_hat" />
	<Definition sku="halloween_axe_hat" category="head" tidName="TID_HALLOWEEN_AXE_HAT" />
	<Definition sku="halloween_pitchfork_hat" category="head" tidName="TID_HALLOWEEN_PITCHFORK_HAT" />
	<Definition sku="halloween_saw_hat" category="head" tidName="TID_HALLOWEEN_SAW_HAT" />
	<Definition sku="halloween_scissors_hat" category="head" tidName="TID_HALLOWEEN_SCISSORS_HAT" />
	<Definition sku="halloween_werewolf_mask" category="head" tidName="TID_HALLOWEEN_WEREWOLF_MASK" />
	<Definition sku="halloween_vampire_mask" category="head" tidName="TID_HALLOWEEN_VAMPIRE_MASK" />
	<Definition sku="halloween_frank_mask" category="head" tidName="TID_HALLOWEEN_FRANK_MASK" />
	<Definition sku="halloween_skull_mask" category="head" tidName="TID_HALLOWEEN_SKULL_MASK" />
	<Definition sku="halloween_witch_hat" category="head" tidName="TID_HALLOWEEN_WITCH_HAT" />
</Definitions>
