{"urlBase":"localhost","assets":{"petMovementDefinitions.xml":{"crc32":0,"size":0,"type":"content"},"turkish.txt":{"crc32":0,"size":0,"type":"content"},"freezeConstantDefinitions.xml":{"crc32":0,"size":0,"type":"content"},"seasonsDefinitions.xml":{"crc32":0,"size":0,"type":"content"},"pets_09":{"crc32":3088997289,"size":1208813,"type":"bundle"},"initialSettings.xml":{"crc32":0,"size":0,"type":"content"},"petDefinitions.xml":{"crc32":0,"size":0,"type":"content"},"pets_08":{"crc32":831143054,"size":2062894,"type":"bundle"},"japanese.txt":{"crc32":0,"size":0,"type":"content"},"dailyRewardsDefinitions.xml":{"crc32":0,"size":0,"type":"content"},"mapUpgradesDefinitions.xml":{"crc32":0,"size":0,"type":"content"},"pets_07":{"crc32":444051481,"size":2677449,"type":"bundle"},"dragonStatsDefinitions.xml":{"crc32":0,"size":0,"type":"content"},"dragonTierDefinitions.xml":{"crc32":0,"size":0,"type":"content"},"tournamentsDefinitions.xml":{"crc32":0,"size":0,"type":"content"},"entityDefinitions.xml":{"crc32":0,"size":0,"type":"content"},"missionDragonModifiersDefinitions.xml":{"crc32":0,"size":0,"type":"content"},"pets_06":{"crc32":2425846722,"size":2614000,"type":"bundle"},"pets_05":{"crc32":2600173771,"size":1372114,"type":"bundle"},"pets_03":{"crc32":3102184729,"size":1292123,"type":"bundle"},"pets_02":{"crc32":3418037452,"size":1341084,"type":"bundle"},"traditional_chinese.txt":{"crc32":0,"size":0,"type":"content"},"pets_01":{"crc32":2155497055,"size":1276931,"type":"bundle"},"specialDragonPowerDefinitions.xml":{"crc32":0,"size":0,"type":"content"},"PM_level_0_area2.xml":{"crc32":0,"size":0,"type":"content"},"spawners_medieval_village_dark":{"crc32":3541754185,"size":4492,"type":"bundle"},"missingRessourcesTiersDefinitions.xml":{"crc32":0,"size":0,"type":"content"},"spawners_medieval_dark":{"crc32":1222894421,"size":11782,"type":"bundle"},"sounds_medieval_village_dark":{"crc32":667001289,"size":154667,"type":"bundle"},"petCategoryDefinitions.xml":{"crc32":0,"size":0,"type":"content"},"sounds_medieval_dark":{"crc32":806735633,"size":2568382,"type":"bundle"},"particles_medieval_dark":{"crc32":469343828,"size":206024,"type":"bundle"},"assets_medieval_dark":{"crc32":2617814670,"size":3839087,"type":"bundle"},"scene_medieval_dark":{"crc32":3083417275,"size":849786,"type":"bundle"},"spawners_medieval_village_castle_dark":{"crc32":453150940,"size":13029,"type":"bundle"},"spawners_medieval_village_castle":{"crc32":227083502,"size":9897,"type":"bundle"},"missionDifficultyDefinitions.xml":{"crc32":0,"size":0,"type":"content"},"spawners_medieval_castle":{"crc32":173555010,"size":7389,"type":"bundle"},"sounds_medieval_village_castle_dark":{"crc32":2654814804,"size":1893153,"type":"bundle"},"english.txt":{"crc32":0,"size":0,"type":"content"},"shareLocationDefinitions.xml":{"crc32":0,"size":0,"type":"content"},"sounds_medieval_village_castle":{"crc32":1552309870,"size":1088521,"type":"bundle"},"hungryLettersDefinitions.xml":{"crc32":0,"size":0,"type":"content"},"sounds_medieval_castle":{"crc32":1469895732,"size":2295894,"type":"bundle"},"particles_medieval_castle":{"crc32":1065169018,"size":50713,"type":"bundle"},"assets_medieval_castle_dark":{"crc32":2082860005,"size":83300,"type":"bundle"},"dragonSettings.xml":{"crc32":0,"size":0,"type":"content"},"assets_medieval_castle":{"crc32":4094420619,"size":9533568,"type":"bundle"},"scene_medieval_castle":{"crc32":3299715845,"size":2693316,"type":"bundle"},"scoreMultiplierDefinitions.xml":{"crc32":0,"size":0,"type":"content"},"localizationDefinitions.xml":{"crc32":0,"size":0,"type":"content"},"chestRewardDefinitions.xml":{"crc32":0,"size":0,"type":"content"},"specialDragonUpgradesDefinitions.xml":{"crc32":0,"size":0,"type":"content"},"npc_medieval_castle":{"crc32":3459720611,"size":2417423,"type":"bundle"},"npc_medieval_dark":{"crc32":2060735048,"size":3142523,"type":"bundle"},"gameSettings.xml":{"crc32":0,"size":0,"type":"content"},"pets_local":{"crc32":1842493511,"size":7598336,"type":"bundle"},"pets_04":{"crc32":1895448237,"size":1288654,"type":"bundle"},"dragon_titan_shared":{"crc32":4283418719,"size":1178036,"type":"bundle"},"survivalBonusDefinitions.xml":{"crc32":0,"size":0,"type":"content"},"PM_level_0_area1.xml":{"crc32":0,"size":0,"type":"content"},"french.txt":{"crc32":0,"size":0,"type":"content"},"levelDefinitions.xml":{"crc32":0,"size":0,"type":"content"},"dragon_titan":{"crc32":2229943700,"size":7598163,"type":"bundle"},"fontGroupsDefinitions.xml":{"crc32":0,"size":0,"type":"content"},"missionSpecialDragonModifiersDefinitions.xml":{"crc32":0,"size":0,"type":"content"},"dragon_jawfrey_shared":{"crc32":1589102188,"size":294284,"type":"bundle"},"dragon_jawfrey":{"crc32":1710617552,"size":6222294,"type":"bundle"},"powerUpsDefinitions.xml":{"crc32":0,"size":0,"type":"content"},"dragon_ice_shared":{"crc32":349720405,"size":189501,"type":"bundle"},"NPC_Pools_level_0_area2.xml":{"crc32":0,"size":0,"type":"content"},"holdPreyTierSettingsDefinitions.xml":{"crc32":0,"size":0,"type":"content"},"dragon_ice":{"crc32":372904130,"size":1501041,"type":"bundle"},"specialDragonTierDefinitions.xml":{"crc32":0,"size":0,"type":"content"},"dragon_helicopter_shared":{"crc32":1737769585,"size":423508,"type":"bundle"},"dragon_helicopter":{"crc32":92769099,"size":2097804,"type":"bundle"},"dragon_hedgehog_shared":{"crc32":686727515,"size":41221,"type":"bundle"},"dragon_hedgehog":{"crc32":1298824316,"size":2062041,"type":"bundle"},"spanish.txt":{"crc32":0,"size":0,"type":"content"},"dragon_goldheist_shared":{"crc32":2547899447,"size":1113361,"type":"bundle"},"missionOtherModifiersDefinitions.xml":{"crc32":0,"size":0,"type":"content"},"preRegRewardsDefinitions.xml":{"crc32":0,"size":0,"type":"content"},"leaguesRewardsDefinitions.xml":{"crc32":0,"size":0,"type":"content"},"modsDefinitions.xml":{"crc32":0,"size":0,"type":"content"},"shopPacksDefinitions.xml":{"crc32":0,"size":0,"type":"content"},"spawnersDragonBurnDefinitions.xml":{"crc32":0,"size":0,"type":"content"},"dragon_goldheist":{"crc32":822855465,"size":4717792,"type":"bundle"},"dragon_fat_shared":{"crc32":934878976,"size":51407,"type":"bundle"},"happyHourDefinitions.xml":{"crc32":0,"size":0,"type":"content"},"dragon_fat":{"crc32":3546829219,"size":5075014,"type":"bundle"},"goldenEggDefinitions.xml":{"crc32":0,"size":0,"type":"content"},"german.txt":{"crc32":0,"size":0,"type":"content"},"simplified_chinese.txt":{"crc32":0,"size":0,"type":"content"},"dragon_electric_shared":{"crc32":3078191116,"size":182598,"type":"bundle"},"dragon_electric":{"crc32":1842332151,"size":735085,"type":"bundle"},"leaguesDefinitions.xml":{"crc32":0,"size":0,"type":"content"},"dragon_dino_shared":{"crc32":2945869714,"size":91923,"type":"bundle"},"specialDragonStatsUpgradesDefinitions.xml":{"crc32":0,"size":0,"type":"content"},"dragon_dino":{"crc32":1214741098,"size":3619452,"type":"bundle"},"achievementsDefinitions.xml":{"crc32":0,"size":0,"type":"content"},"dragonProgressionDefinitions.xml":{"crc32":0,"size":0,"type":"content"},"eggRewardDefinitions.xml":{"crc32":0,"size":0,"type":"content"},"PM_level_0_common.xml":{"crc32":0,"size":0,"type":"content"},"italian.txt":{"crc32":0,"size":0,"type":"content"},"dragon_devil_shared":{"crc32":4017729446,"size":367352,"type":"bundle"},"dragon_devil":{"crc32":180039733,"size":6834262,"type":"bundle"},"offerPacksDefinitions.xml":{"crc32":0,"size":0,"type":"content"},"dragon_dark_shared":{"crc32":2994137275,"size":126396,"type":"bundle"},"dragon_dark":{"crc32":69487981,"size":4921922,"type":"bundle"},"dragon_classic_shared":{"crc32":1749589205,"size":1029872,"type":"bundle"},"NPC_Pools_level_0_common.xml":{"crc32":0,"size":0,"type":"content"},"missingRessourcesVariablesDefinitions.xml":{"crc32":0,"size":0,"type":"content"},"korean.txt":{"crc32":0,"size":0,"type":"content"},"dailyRewardsDragonModifiersDefinitions.xml":{"crc32":0,"size":0,"type":"content"},"featureDeviceSettings.xml":{"crc32":0,"size":0,"type":"content"},"featureProfileSettings.xml":{"crc32":0,"size":0,"type":"content"},"levelSpawnPointDefinitions.xml":{"crc32":0,"size":0,"type":"content"},"specialDragonDefinitions.xml":{"crc32":0,"size":0,"type":"content"},"dragon_classic":{"crc32":2092565603,"size":8023553,"type":"bundle"},"dragon_chinese_shared":{"crc32":2049674706,"size":783311,"type":"bundle"},"dragon_chinese":{"crc32":704850768,"size":3629558,"type":"bundle"},"dynamicGatchaDefinition.xml":{"crc32":0,"size":0,"type":"content"},"levelProgressionDefinitions.xml":{"crc32":0,"size":0,"type":"content"},"dragon_bug_shared":{"crc32":1254644332,"size":1189998,"type":"bundle"},"shared_characters.txt":{"crc32":0,"size":0,"type":"content"},"interstitialAdsSettingsDefinitions.xml":{"crc32":0,"size":0,"type":"content"},"dragon_bug":{"crc32":297576061,"size":5229828,"type":"bundle"},"missionTypeDefinitions.xml":{"crc32":0,"size":0,"type":"content"},"shared":{"crc32":1112237660,"size":2998654,"type":"bundle"},"particles_shared":{"crc32":1383470962,"size":1881179,"type":"bundle"},"particles_medieval_village_dark":{"crc32":2544550010,"size":31863,"type":"bundle"},"particles_medieval_village_castle_dark":{"crc32":830001022,"size":220423,"type":"bundle"},"particles_medieval_village":{"crc32":3845092331,"size":42389,"type":"bundle"},"PM_level_0_area3.xml":{"crc32":0,"size":0,"type":"content"},"disguisesDefinitions.xml":{"crc32":0,"size":0,"type":"content"},"specialMissionDifficultyDefinitions.xml":{"crc32":0,"size":0,"type":"content"},"npc_shared":{"crc32":300081290,"size":218819,"type":"bundle"},"missionDifficultyModifiersDefinitions.xml":{"crc32":0,"size":0,"type":"content"},"iconDefinitions.xml":{"crc32":0,"size":0,"type":"content"},"interstitialAdsProfilesDefinitions.xml":{"crc32":0,"size":0,"type":"content"},"npc_medieval_village_dark":{"crc32":1383403899,"size":1479847,"type":"bundle"},"eggDefinitions.xml":{"crc32":0,"size":0,"type":"content"},"NPC_Pools_level_0_area1.xml":{"crc32":0,"size":0,"type":"content"},"specialDisguisesDefinitions.xml":{"crc32":0,"size":0,"type":"content"},"npc_medieval_village_castle_dark":{"crc32":2842561158,"size":5343000,"type":"bundle"},"npc_medieval_village_castle":{"crc32":778022252,"size":1706063,"type":"bundle"},"entityDragonBurnDefinitions.xml":{"crc32":0,"size":0,"type":"content"},"notificationsDefinitions.xml":{"crc32":0,"size":0,"type":"content"},"dragonHealthModifiersDefinitions.xml":{"crc32":0,"size":0,"type":"content"},"npc_medieval_village":{"crc32":4267874373,"size":371693,"type":"bundle"},"dragon_shared_ingame":{"crc32":2949111828,"size":511172,"type":"bundle"},"decorationDefinitions.xml":{"crc32":0,"size":0,"type":"content"},"missionsDefinitions.xml":{"crc32":0,"size":0,"type":"content"},"dragon_shared":{"crc32":3578626794,"size":25721,"type":"bundle"},"deviceRatingSettings.xml":{"crc32":0,"size":0,"type":"content"},"dragon_balrog_shared":{"crc32":3001598729,"size":825663,"type":"bundle"},"assets_medieval_village_dark":{"crc32":3588539116,"size":3086714,"type":"bundle"},"dragonDefinitions.xml":{"crc32":0,"size":0,"type":"content"},"rarityDefinitions.xml":{"crc32":0,"size":0,"type":"content"},"NPC_Pools_level_0_area3.xml":{"crc32":0,"size":0,"type":"content"},"equipableDefinitions.xml":{"crc32":0,"size":0,"type":"content"},"assets_medieval_village_castle_dark":{"crc32":2598750396,"size":6273702,"type":"bundle"},"entityCategoryDefinitions.xml":{"crc32":0,"size":0,"type":"content"},"russian.txt":{"crc32":0,"size":0,"type":"content"},"assets_medieval_village_castle":{"crc32":1644998989,"size":4431004,"type":"bundle"},"brazilian.txt":{"crc32":0,"size":0,"type":"content"},"dragon_balrog":{"crc32":2495942325,"size":5569051,"type":"bundle"}},"release":"2.0.0","deltas":0,"revision":5,"bundlesBase":"AssetBundles"}