{"urlBase":"http://10.44.4.76:7888/iOS/","assets":{"dragon_balrog":{"crc32":751806757,"size":5670016},"dragon_bug":{"crc32":2202944727,"size":6204557},"dragon_chinese":{"crc32":1593242854,"size":3722396},"dragon_classic":{"crc32":2121996837,"size":8219205},"dragon_dark":{"crc32":3967621556,"size":5234907},"dragon_devil":{"crc32":3870626283,"size":6757795},"dragon_dino":{"crc32":165278196,"size":3772536},"dragon_electric":{"crc32":4269756020,"size":737836},"dragon_fat":{"crc32":3686615153,"size":5059539},"dragon_goldheist":{"crc32":37261728,"size":4692500},"dragon_hedgehog":{"crc32":263260176,"size":2118270},"dragon_helicopter":{"crc32":376532842,"size":2096994},"dragon_ice":{"crc32":1761244454,"size":1499665},"dragon_jawfrey":{"crc32":1810741116,"size":7401012},"dragon_titan":{"crc32":519057406,"size":8577184},"pets_04":{"crc32":980385038,"size":1037798},"npc_medieval_dark":{"crc32":4023967771,"size":3583485},"npc_medieval_castle":{"crc32":1595636368,"size":3447586},"scene_medieval_castle":{"crc32":1173432218,"size":2638419},"assets_medieval_castle":{"crc32":2051402157,"size":10435862},"assets_medieval_castle_dark":{"crc32":1996786115,"size":74351},"particles_medieval_castle":{"crc32":139632395,"size":46412},"sounds_medieval_castle":{"crc32":341304947,"size":2295894},"spawners_medieval_castle":{"crc32":1220443976,"size":7388},"scene_medieval_dark":{"crc32":3981514571,"size":888311},"assets_medieval_dark":{"crc32":3711923952,"size":3220136},"particles_medieval_dark":{"crc32":2852124884,"size":151134},"sounds_medieval_dark":{"crc32":2519657168,"size":2568382},"spawners_medieval_dark":{"crc32":1020440216,"size":11782},"pets_01":{"crc32":3419903301,"size":983617},"pets_02":{"crc32":2871326605,"size":1078325},"pets_03":{"crc32":1459880557,"size":1068188},"pets_05":{"crc32":1275117608,"size":1067972},"pets_06":{"crc32":2205819959,"size":2279458},"pets_07":{"crc32":4207140927,"size":2482048},"pets_08":{"crc32":331193077,"size":1813918},"pets_09":{"crc32":2294759734,"size":1248872},"dragon_baby_animoji":{"crc32":2874244747,"size":3961741},"dragon_bug_animoji":{"crc32":3429768886,"size":3059575},"dragon_chinese_animoji":{"crc32":1490918313,"size":596802},"dragon_classic_animoji":{"crc32":2507266679,"size":3560960},"dragon_goldheist_animoji":{"crc32":4074381625,"size":2353182},"dragon_reptile_animoji":{"crc32":3081412543,"size":3067297},"dragon_titan_animoji":{"crc32":705825684,"size":1238662}}}
